dllproxy/__init__.py
dllproxy/generate.py
dllproxy/template/Config.hpp
dllproxy/template/DllProxy.sln
dllproxy/template/DllProxy.vcxproj
dllproxy/template/DllProxy.vcxproj.filters
dllproxy/template/Main.cpp
dllproxy/template/Project.props
dllproxy/template/SingleRuntimeGuard.cpp
dllproxy/template/SingleRuntimeGuard.hpp
dllproxy/template/Source.def
dllproxy/template/Worker.cpp
dllproxy/template/Worker.hpp
dllproxy/template/Framework/ErrorCode.hpp
dllproxy/template/Framework/Event.cpp
dllproxy/template/Framework/Event.hpp
dllproxy/template/Framework/Exception.cpp
dllproxy/template/Framework/Exception.hpp
dllproxy/template/Framework/IRunner.hpp
dllproxy/template/Framework/IWaitable.cpp
dllproxy/template/Framework/IWaitable.hpp
dllproxy/template/Framework/Library.cpp
dllproxy/template/Framework/Library.hpp
dllproxy/template/Framework/Mutex.cpp
dllproxy/template/Framework/Mutex.hpp
dllproxy/template/Framework/ScopedHandle.cpp
dllproxy/template/Framework/ScopedHandle.hpp
dllproxy/template/Framework/Thread.cpp
dllproxy/template/Framework/Thread.hpp
dllproxy/template/Framework/Protections/AbortBehavior.cpp
dllproxy/template/Framework/Protections/AbortBehavior.hpp
dllproxy/template/Framework/Protections/EntryPointProtector.hpp
dllproxy/template/Framework/Protections/ErrorMode.cpp
dllproxy/template/Framework/Protections/ErrorMode.hpp
dllproxy/template/Framework/Protections/InvalidParameter.cpp
dllproxy/template/Framework/Protections/InvalidParameter.hpp
dllproxy/template/Framework/Protections/LibraryProtector.hpp
dllproxy/template/Framework/Protections/ProgramProtector.hpp
dllproxy/template/Framework/Protections/PureCall.cpp
dllproxy/template/Framework/Protections/PureCall.hpp
dllproxy/template/Framework/Protections/StructuredExceptionTranslator.cpp
dllproxy/template/Framework/Protections/StructuredExceptionTranslator.hpp
dllproxy/template/Framework/Protections/TerminationHandler.cpp
dllproxy/template/Framework/Protections/TerminationHandler.hpp
dllproxy-1.0.0.dist-info/licenses/LICENSE
dllproxy-1.0.0.dist-info/METADATA
dllproxy-1.0.0.dist-info/WHEEL
dllproxy-1.0.0.dist-info/entry_points.txt
dllproxy-1.0.0.dist-info/top_level.txt
dllproxy-1.0.0.dist-info/RECORD
