Metadata-Version: 2.4
Name: dllproxy
Version: 1.0.0
Summary: Generate And Build a Windows DLL Proxy For Any DLL
Home-page: https://github.com/gilgoolon/dllproxy
Author: Gil Alpert
Author-email: alpertgil@gmail.com
License: MIT
License-File: LICENSE
Requires-Dist: pefile
Dynamic: author
Dynamic: author-email
Dynamic: description
Dynamic: description-content-type
Dynamic: home-page
Dynamic: license
Dynamic: license-file
Dynamic: requires-dist
Dynamic: summary
